{
    "Name": "Tainted Mag",
    "Type": "Rifle",
    "Polarity": "Naramon",
    "Stats": [
        "Rank",
        "Magazine Capacity",
        "Reload Speed",
        "Cost"
    ],
    "Mod": [
        {
            "Rank": "0",
            "Magazine Capacity": "+6%",
            "Reload Speed": "-3%",
            "Cost": "4"
        },
        {
            "Rank": "1",
            "Magazine Capacity": "+12%",
            "Reload Speed": "-6%",
            "Cost": "5"
        },
        {
            "Rank": "2",
            "Magazine Capacity": "+18%",
            "Reload Speed": "-9%",
            "Cost": "6"
        },
        {
            "Rank": "3",
            "Magazine Capacity": "+24%",
            "Reload Speed": "-12%",
            "Cost": "7"
        },
        {
            "Rank": "4",
            "Magazine Capacity": "+30%",
            "Reload Speed": "-15%",
            "Cost": "8"
        },
        {
            "Rank": "5",
            "Magazine Capacity": "+36%",
            "Reload Speed": "-18%",
            "Cost": "9"
        },
        {
            "Rank": "6",
            "Magazine Capacity": "+42%",
            "Reload Speed": "-21%",
            "Cost": "10"
        },
        {
            "Rank": "7",
            "Magazine Capacity": "+48%",
            "Reload Speed": "-24%",
            "Cost": "11"
        },
        {
            "Rank": "8",
            "Magazine Capacity": "+54%",
            "Reload Speed": "-27%",
            "Cost": "12"
        },
        {
            "Rank": "9",
            "Magazine Capacity": "+60%",
            "Reload Speed": "-30%",
            "Cost": "13"
        },
        {
            "Rank": "10",
            "Magazine Capacity": "+66%",
            "Reload Speed": "-33%",
            "Cost": "14"
        }
    ]
}